asap/__init__.py
asap/cli.py
asap/agent/__init__.py
asap/agent/main.py
asap/agent/utils/__init__.py
asap/agent/utils/agents/__init__.py
asap/agent/utils/agents/config.py
asap/agent/utils/agents/factory_agent.py
asap/agent/utils/agents/migration_assistant_agent.py
asap/agent/utils/agents/tools/__init__.py
asap/agent/utils/agents/tools/debug/debug_tool.py
asap/agent/utils/agents/tools/general/llamagers.py
asap/agent/utils/agents/tools/general/prompts.py
asap/agent/utils/agents/tools/general/tools_input_class.py
asap/agent/utils/agents/tools/translate/translate_tools.py
asap/agent/utils/general/ui.py
asap_cli-0.0.3.dist-info/METADATA
asap_cli-0.0.3.dist-info/WHEEL
asap_cli-0.0.3.dist-info/entry_points.txt
asap_cli-0.0.3.dist-info/top_level.txt
asap_cli-0.0.3.dist-info/RECORD
