Metadata-Version: 2.4
Name: asap-cli
Version: 0.0.3
Summary: ASAP CLI Tool
Author-email: Jorge Sierra <jorsie@amazon.com>
Requires-Python: >=3.10
Requires-Dist: langgraph==0.6.4
Requires-Dist: langchain-aws==0.2.30
Requires-Dist: langchain==0.3.27
Requires-Dist: python-dotenv==1.1.1
Requires-Dist: langchain-community==0.3.27
Requires-Dist: langgraph-checkpoint==2.1.1
Requires-Dist: boto3==1.40.8
Requires-Dist: pandas==2.3.2
Requires-Dist: tabulate==0.9.0
Requires-Dist: pyfiglet==1.0.4
Requires-Dist: rich==14.1.0
Requires-Dist: typer[all]==0.16.1
